jiggler.py
jiggler-0.0.3.dist-info/LICENSE
jiggler-0.0.3.dist-info/METADATA
jiggler-0.0.3.dist-info/WHEEL
jiggler-0.0.3.dist-info/entry_points.txt
jiggler-0.0.3.dist-info/top_level.txt
jiggler-0.0.3.dist-info/RECORD
