Metadata-Version: 2.1
Name: jiggler
Version: 0.0.3
Summary: Keep your screen awake and working while you rest
Home-page: https://github.com/InvincibleZeal/jiggler
Author: Ritesh Ganjewala
Author-email: ritesh.ganjewala17@gmail.com
License: MIT
Classifier: Intended Audience :: End Users/Desktop
Classifier: Topic :: Utilities
Classifier: Topic :: Terminals
Classifier: Operating System :: MacOS :: MacOS X
Classifier: Operating System :: Microsoft :: Windows :: Windows NT/2000
Classifier: Operating System :: POSIX
Classifier: License :: OSI Approved :: MIT License
Classifier: Programming Language :: Python
Classifier: Programming Language :: Python :: 3.4
Classifier: Programming Language :: Python :: 3.5
Classifier: Programming Language :: Python :: 3.6
Classifier: Programming Language :: Python :: 3.7
Classifier: Programming Language :: Python :: 3.8
Classifier: Programming Language :: Python :: 3.9
Classifier: Programming Language :: Python :: 3.9
Requires-Python: >=3
License-File: LICENSE
Requires-Dist: click >=7
Requires-Dist: pynput >=1
